pycwatch/cli/__init__.py
pycwatch/cli/assets.py
pycwatch/cli/exchanges.py
pycwatch/cli/main.py
pycwatch/cli/markets.py
pycwatch/cli/pairs.py
pycwatch/cli/py.typed
pycwatch/cli/utils.py
pycwatch_cli-2.1.2.dist-info/METADATA
pycwatch_cli-2.1.2.dist-info/WHEEL
pycwatch_cli-2.1.2.dist-info/entry_points.txt
pycwatch_cli-2.1.2.dist-info/RECORD
