Metadata-Version: 2.1
Name: pycwatch-cli
Version: 2.1.2
Summary: A CLI application for the Cryptowatch Rest API.
Home-page: https://github.com/ljnsn/pycwatch
License: MIT
Keywords: cryptocurrency,crypto,prices,cryptowatch
Author: ljnsn
Author-email: 82611987+ljnsn@users.noreply.github.com
Requires-Python: >=3.10,<4.0
Classifier: Development Status :: 5 - Production/Stable
Classifier: Environment :: Web Environment
Classifier: Intended Audience :: Developers
Classifier: License :: OSI Approved :: MIT License
Classifier: Operating System :: OS Independent
Classifier: Programming Language :: Python
Classifier: Programming Language :: Python :: 3
Classifier: Programming Language :: Python :: 3.10
Classifier: Programming Language :: Python :: 3.11
Classifier: Programming Language :: Python :: 3.7
Classifier: Programming Language :: Python :: 3.8
Classifier: Programming Language :: Python :: 3.9
Classifier: Topic :: Internet :: WWW/HTTP :: Dynamic Content
Provides-Extra: test
Requires-Dist: black (>=22.1,<24.0) ; extra == "test"
Requires-Dist: coverage[toml] (>=6.3.2,<8.0.0) ; extra == "test"
Requires-Dist: mypy (>=0.931) ; extra == "test"
Requires-Dist: pre-commit (<4.0) ; extra == "test"
Requires-Dist: pycwatch-lib (==2.1.2)
Requires-Dist: pytest (>=7.0.1) ; extra == "test"
Requires-Dist: pytest-cov (>=3,<5) ; extra == "test"
Requires-Dist: rich (>=13.5.2,<14.0.0)
Requires-Dist: ruff (>=0.0.253) ; extra == "test"
Requires-Dist: typer (>=0.9.0,<0.10.0)
Project-URL: Repository, https://github.com/ljnsn/pycwatch
